HISTORY.txt
LICENSE.txt
MANIFEST.in
README.md
setup.cfg
setup.py
sparc/__init__.py
sparc.cache.egg-info/PKG-INFO
sparc.cache.egg-info/SOURCES.txt
sparc.cache.egg-info/dependency_links.txt
sparc.cache.egg-info/entry_points.txt
sparc.cache.egg-info/namespace_packages.txt
sparc.cache.egg-info/not-zip-safe
sparc.cache.egg-info/requires.txt
sparc.cache.egg-info/top_level.txt
sparc/cache/__init__.py
sparc/cache/configure.zcml
sparc/cache/interfaces.py
sparc/cache/item.py
sparc/cache/sql.py
sparc/cache/sources/__init__.py
sparc/cache/sources/configure.zcml
sparc/cache/sources/csvdata.py
sparc/cache/sources/interfaces.py
sparc/cache/sources/normalized_datetime.py
sparc/cache/sources/tests/__init__.py
sparc/cache/sources/tests/test_csvdata.py
sparc/cache/tests/__init__.py
sparc/cache/tests/test_sql.py